{"owners": [1], "_access": {"metadata_restricted": false, "files_restricted": false}, "title": "Synthesis and characterization of meso-substituted tetrabenzoporphyrin complexes with Pt(II) and Pd(II) for optical oxygen sensing", "publicationDatePure": "2009", "createdDatePure": "2016-02-25T21:52:49.273+0000", "modifiedDatePure": "2018-09-06T07:29:19.657+0000", "pureId": "1083612", "uuid": "0f1d01e8-fd22-41e6-b449-131a5207b72f", "type_p": "Poster", "category": "Research", "peerReview": "False", "publicationStatus": "Published", "language": "eng", "totalNumberOfAuthors": "3", "managingOrganisationalUnit": "Institute of Analytical Chemistry and Food Chemistry (6450)", "workflow": "For validation", "confidential": "False", "access_right": "closed", "description": "TEST DESCRIPTION", "additional_descriptions": [{"description": "this is my additional description"}], "additional_titles": [{"title": "this is my additional title"}], "contributors": [{"name": "Borisov, Sergey", "personRole": "Author", "organisationalUnit": "Institute of Analytical Chemistry and Food Chemistry (6450)", "link": "https://pure01.tugraz.at/ws/api/514/persons/71e2b8cb-543d-4e47-a013-865ff434b5c2"}, {"name": "DeToma, Alaina S", "personRole": "Author", "link": "https://pure01.tugraz.at/ws/api/514/external-persons/0e434ef6-86ea-4f3b-8aab-3f7cee7cd396", "type_p": "External person"}, {"name": "Klimant, Ingo", "personRole": "Author", "organisationalUnit": "Institute of Analytical Chemistry and Food Chemistry (6450)", "link": "https://pure01.tugraz.at/ws/api/514/persons/f661d36c-be32-4b8e-be74-3dd0fa657b6c"}], "organisationalUnits": [{"name": "Institute of Analytical Chemistry and Food Chemistry (6450)", "link": "https://pure01.tugraz.at/ws/api/514/organisational-units/95389b7a-4be9-4f64-8491-0dd9b3e5f041"}]}