{"access_right": "open", "owners": [1], "_access": {"metadata_restricted": false, "files_restricted": false}, "title": "Beurteilung der Umweltverträglichkeit des Einsatzes von Einjahresganzpflanzen und Stroh zur Fernwärmeerzeugung, Endbericht", "publicationDatePure": "1997", "createdDatePure": "2016-02-25T21:47:56.410+0000", "modifiedDatePure": "2018-09-06T07:28:34.742+0000", "pureId": "1064125", "uuid": "4dabd5dc-2610-4b5a-b72c-83b480341998", "type_p": "Other report", "category": "Research", "peerReview": "False", "publicationStatus": "Published", "language": "deu", "totalNumberOfAuthors": "4", "managingOrganisationalUnit": "Institute of Process and Particle Engineering (6690)", "workflow": "For validation", "confidential": "False", "publisherName": ".", "accessType": "None", "contributors": [{"name": "Obernberger, Ingwald", "personRole": "Author", "organisationalUnit": "Institute of Process and Particle Engineering (6690)", "link": "https://pure01.tugraz.at/ws/api/514/persons/5295ba8b-5bc3-48b7-b704-dfabceea4eab"}, {"name": "Widmann, Walter", "personRole": "Author", "link": "https://pure01.tugraz.at/ws/api/514/external-persons/221f7374-bfd1-4634-a6f3-17887c66cc99", "type_p": "External person"}, {"name": "Wurst, Friedrich", "personRole": "Author", "link": "https://pure01.tugraz.at/ws/api/514/external-persons/842de480-f122-4d8b-aabf-677d5ea1b50b", "type_p": "External person"}, {"name": "Wörgetter, Manfred", "personRole": "Author", "link": "https://pure01.tugraz.at/ws/api/514/external-persons/ecef45ac-084a-48e8-85ad-d71aa2312030", "type_p": "External person"}], "organisationalUnits": [{"name": "Institute of Process and Particle Engineering (6690)", "link": "https://pure01.tugraz.at/ws/api/514/organisational-units/44dff43c-2d42-4974-98d8-b249db092dbc"}]}